tkVideoPlayer/__init__.py
tkVideoPlayer/tkvideoplayer.py
tkvideoplayer-2.4.dist-info/LICENSE
tkvideoplayer-2.4.dist-info/METADATA
tkvideoplayer-2.4.dist-info/WHEEL
tkvideoplayer-2.4.dist-info/top_level.txt
tkvideoplayer-2.4.dist-info/RECORD
