Metadata-Version: 2.1
Name: tkvideoplayer
Version: 2.4
Summary: This library helps you play video files in tkinter
Home-page: https://github.com/PaulleDemon/tkVideoPlayer
Author: Paul
License: MIT
Keywords: tkinter,video,player,video player,tkvideoplayer,play video in tkinter
Classifier: License :: OSI Approved :: MIT License
Classifier: Development Status :: 5 - Production/Stable
Classifier: Programming Language :: Python :: 3.6
Classifier: Programming Language :: Python :: 3.7
Classifier: Programming Language :: Python :: 3.8
Classifier: Programming Language :: Python :: 3.9
Classifier: Programming Language :: Python :: 3.10
Requires-Python: >=3.6
License-File: LICENSE
Requires-Dist: av
Requires-Dist: pillow
